easyjsonparser/__init__.py
easyjsonparser/array.py
easyjsonparser/document.py
easyjsonparser/expressions.py
easyjsonparser/helper.py
easyjsonparser/instance.py
easyjsonparser/numbers.py
easyjsonparser/object.py
easyjsonparser/string.py
easyjsonparser/value.py
easyjsonparser-1.0.0.dist-info/LICENSE
easyjsonparser-1.0.0.dist-info/METADATA
easyjsonparser-1.0.0.dist-info/WHEEL
easyjsonparser-1.0.0.dist-info/top_level.txt
easyjsonparser-1.0.0.dist-info/RECORD
