Metadata-Version: 2.1
Name: easyjsonparser
Version: 1.0.0
Summary: Serialize and deserialize JSON documents to Python data structures
Home-page: https://github.com/xatavian/easyjsonparser
Author: Avi SZYCHTER
Author-email: xentsc2@gmail.com
License: UNKNOWN
Platform: UNKNOWN
Classifier: Programming Language :: Python :: 3
Classifier: License :: OSI Approved :: MIT License
Classifier: Operating System :: OS Independent
